chat_object/__init__.py
chat_object/chat_obj.py
chat_object/consts.py
chat_object/message.py
chat_object/prompt.py
chat_object/qol.py
chat_object/role.py
chat_object-2.0.2.dist-info/licenses/LICENSE.txt
chat_object-2.0.2.dist-info/METADATA
chat_object-2.0.2.dist-info/WHEEL
chat_object-2.0.2.dist-info/top_level.txt
chat_object-2.0.2.dist-info/RECORD
