Metadata-Version: 2.4
Name: chat-object
Version: 2.0.2
Summary: A simple library for creating and manipulating chat and message objects for LLM applications
Author: fresh-milkshake
License: MIT License
Requires-Python: >=3.10
License-File: LICENSE.txt
Provides-Extra: dev
Requires-Dist: ruff; extra == "dev"
Requires-Dist: rich; extra == "dev"
Requires-Dist: python-dotenv>=1.1.1; extra == "dev"
Dynamic: license-file
